poverty/__init__.py
poverty/__version__.py
poverty/guidelines.py
poverty/povertylevel.py
poverty/state.py
povertylevel-0.0.5.dist-info/LICENSE
povertylevel-0.0.5.dist-info/METADATA
povertylevel-0.0.5.dist-info/WHEEL
povertylevel-0.0.5.dist-info/top_level.txt
povertylevel-0.0.5.dist-info/RECORD
