Metadata-Version: 2.1
Name: povertylevel
Version: 0.0.5
Summary: U.S. federal poverty level guidelines used to determine financial eligibility for certain federal programs
Home-page: https://github.com/bryand1/python-poverty-level
Author: Bryan Andrade
Author-email: me@bryanandrade.com
License: MIT
Platform: UNKNOWN
Classifier: Development Status :: 3 - Alpha
Classifier: License :: OSI Approved :: MIT License
Classifier: Intended Audience :: Developers
Classifier: Natural Language :: English
Classifier: Programming Language :: Python
Classifier: Programming Language :: Python :: 3
Classifier: Programming Language :: Python :: 3.6
Classifier: Programming Language :: Python :: 3.7
Classifier: Programming Language :: Python :: Implementation :: CPython
Requires-Python: >=3.6.0
